pygemstones/__init__.py
pygemstones/io/__init__.py
pygemstones/io/file.py
pygemstones/io/net.py
pygemstones/io/pack.py
pygemstones/system/bootstrap.py
pygemstones/system/env.py
pygemstones/system/platform.py
pygemstones/system/runner.py
pygemstones/system/settings.py
pygemstones/type/__init__.py
pygemstones/type/list.py
pygemstones/type/string.py
pygemstones/util/__init__.py
pygemstones/util/log.py
pygemstones/vendor/__init__.py
pygemstones/vendor/aws.py
pygemstones-0.0.14.dist-info/LICENSE
pygemstones-0.0.14.dist-info/METADATA
pygemstones-0.0.14.dist-info/WHEEL
pygemstones-0.0.14.dist-info/RECORD
