Metadata-Version: 2.1
Name: pygemstones
Version: 0.0.14
Summary: Python package that group a lot of classes and functions that help software development.
Home-page: https://github.com/paulocoutinhox/pygemstones
License: MIT
Author: Paulo Coutinho
Author-email: paulocoutinhox@gmail.com
Requires-Python: >=3.7.0,<4.0.0
Classifier: License :: OSI Approved :: MIT License
Classifier: Programming Language :: Python :: 3
Classifier: Programming Language :: Python :: 3.7
Classifier: Programming Language :: Python :: 3.8
Classifier: Programming Language :: Python :: 3.9
Classifier: Programming Language :: Python :: 3.10
Classifier: Programming Language :: Python :: 3.11
Classifier: Programming Language :: Python :: 3.12
Classifier: Topic :: Software Development :: Libraries :: Python Modules
Requires-Dist: boto3 (>=1.20.10,<2.0.0)
Requires-Dist: colorama (>=0.4.4,<0.5.0)
Project-URL: Documentation, https://github.com/paulocoutinhox/pygemstones
Project-URL: Repository, https://github.com/paulocoutinhox/pygemstones
